market_database/__init__.py
market_database/common/__init__.py
market_database/common/types.py
market_database/common/utils.py
market_database/configs/__init__.py
market_database/configs/ticker_figi_map.json
market_database/keeper/__init__.py
market_database/keeper/data_keeper.py
market_database/seeker/__init__.py
market_database/seeker/history_seeker.py
market_database/seeker/utils.py
market_database-1.0.4.dist-info/METADATA
market_database-1.0.4.dist-info/WHEEL
market_database-1.0.4.dist-info/top_level.txt
market_database-1.0.4.dist-info/RECORD
